{
  "status": true,
  "message": "successfully fetched all the Contacts data",
  "data": [
    {
      "id": 1,
      "phone": "01798-980272",
      "section_no": "C",
      "name": "নাজিব বিন তাহের"
    },
    {
      "id": 2,
      "phone": "01617-201802",
      "section_no": "C",
      "name": "ইসতিয়াক হোসেন"
    },
    {
      "id": 3,
      "phone": "01616-774903",
      "section_no": "C",
      "name": "রাহাত বিন আলিম"
    },
    {
      "id": 4,
      "phone": "",
      "section_no": "C",
      "name": "শাশ্বত হক"
    },
    {
      "id": 5,
      "phone": "",
      "section_no": "C",
      "name": "আরিফ ইসতিয়াক"
    },
    {
      "id": 6,
      "phone": "01617-201806",
      "section_no": "C",
      "name": "মোঃ মারুফ হোসেন"
    },
    {
      "id": 7,
      "phone": "",
      "section_no": "C",
      "name": "নিহাল হাসনাইন"
    },
    {
      "id": 8,
      "phone": "01747-374222",
      "section_no": "C",
      "name": "মোঃ তৌহিদ হাসান"
    },
    {
      "id": 9,
      "phone": "01617-201809",
      "section_no": "C",
      "name": "মোঃ রিদওয়ানুর রহমান"
    },
    {
      "id": 10,
      "phone": "01829-995649",
      "section_no": "C",
      "name": "মোঃ নূর সিদ্দিক রুমান"
    },
    {
      "id": 11,
      "phone": "",
      "section_no": "C",
      "name": "ইয়াসির আরাফাত"
    },
    {
      "id": 12,
      "phone": "01601-979713",
      "section_no": "C",
      "name": "ফারহান লাবিব"
    },
    {
      "id": 13,
      "phone": "01925-239525",
      "section_no": "C",
      "name": "ইফতেখার রহমান"
    },
    {
      "id": 14,
      "phone": "01630-253160",
      "section_no": "C",
      "name": "সাঈদ আল মাহমুদ"
    },
    {
      "id": 15,
      "phone": "",
      "section_no": "C",
      "name": "সাবিত আহম্মেদ"
    },
    {
      "id": 16,
      "phone": "",
      "section_no": "C",
      "name": "তাহমিদুর রহমান"
    },
    {
      "id": 17,
      "phone": "01701-087141",
      "section_no": "C",
      "name": "মেহেদী হাসান"
    },
    {
      "id": 18,
      "phone": "",
      "section_no": "C",
      "name": "মোঃ রেজোয়ান"
    },
    {
      "id": 19,
      "phone": "",
      "section_no": "C",
      "name": "মোঃ ফারহান বাসিম"
    },
    {
      "id": 20,
      "phone": "",
      "section_no": "C",
      "name": "মোঃ নাজমুস সাকিব ( রাইন )"
    },
    {
      "id": 21,
      "phone": "01617-201821",
      "section_no": "C",
      "name": "নিহাল হাসিন"
    },
    {
      "id": 22,
      "phone": "01733-546415",
      "section_no": "C",
      "name": "মোঃ ফয়সাল আহম্মেদ (সজিব)"
    },
    {
      "id": 23,
      "phone": "",
      "section_no": "C",
      "name": "তৌহিদ আহানাফ ( মুগ্ধ )"
    },
    {
      "id": 24,
      "phone": "",
      "section_no": "C",
      "name": "মোঃ মেহেদী হাসান"
    },
    {
      "id": 25,
      "phone": "01703-750565",
      "section_no": "C",
      "name": "রাওহা সিদ্দিকী রিয়াদ"
    },
    {
      "id": 26,
      "phone": "01732-294213",
      "section_no": "C",
      "name": "নূর ইবনে কাওছার জিতু"
    },
    {
      "id": 27,
      "phone": "",
      "section_no": "C",
      "name": "রাকিব রেজওয়ান ( শুভ )"
    },
    {
      "id": 28,
      "phone": "01735-136366",
      "section_no": "C",
      "name": "মুনতাসির রহমান ( হামীম )"
    },
    {
      "id": 29,
      "phone": "01884-990517",
      "section_no": "C",
      "name": "জুনায়েদ আনজুম"
    },
    {
      "id": 30,
      "phone": "01946-300980",
      "section_no": "C",
      "name": "কাজী ফাহিম আবরার"
    },
    {
      "id": 31,
      "phone": "01770-187659",
      "section_no": "C",
      "name": "এজাজুল হক ( সাকিন )"
    },
    {
      "id": 32,
      "phone": "",
      "section_no": "C",
      "name": "আব্দুল্লাহ সরকার ( জয় )"
    },
    {
      "id": 33,
      "phone": "01938-439946",
      "section_no": "C",
      "name": "মোস্তফা কামরুজ্জামান"
    },
    {
      "id": 34,
      "phone": "01755-266873",
      "section_no": "C",
      "name": "মাহফুজুল হক শাফী"
    },
    {
      "id": 35,
      "phone": "01786-066183",
      "section_no": "C",
      "name": "মোহাইমিনুল ইসলাম"
    },
    {
      "id": 36,
      "phone": "",
      "section_no": "C",
      "name": "মাহির শাহারিয়ার খান"
    },
    {
      "id": 37,
      "phone": "01714-859177",
      "section_no": "C",
      "name": "শৈশব আহম্মেদ"
    },
    {
      "id": 38,
      "phone": "",
      "section_no": "C",
      "name": "রেজওআন ( শাওন )"
    },
    {
      "id": 39,
      "phone": "01568-629974",
      "section_no": "C",
      "name": "তোফায়েল আহম্মেদ"
    },
    {
      "id": 40,
      "phone": "01737-117042",
      "section_no": "C",
      "name": "মোঃ মিরাজুল হাসান হিমেল"
    },
    {
      "id": 41,
      "phone": "01796-715305",
      "section_no": "C",
      "name": "শোয়েব আকতার"
    },
    {
      "id": 42,
      "phone": "01704-829560",
      "section_no": "C",
      "name": "মোঃ শাফিন"
    },
    {
      "id": 43,
      "phone": "",
      "section_no": "C",
      "name": "ফারহান রায়েদ সুদিপ্ত"
    },
    {
      "id": 44,
      "phone": "",
      "section_no": "C",
      "name": "এ.এস.এম. ঈসা"
    },
    {
      "id": 45,
      "phone": "01600-334345",
      "section_no": "C",
      "name": "তানজীমুল হোসেন ( তানিম )"
    },
    {
      "id": 46,
      "phone": "01521-710085",
      "section_no": "C",
      "name": "কিফায়াতুল্লাহ"
    },
    {
      "id": 47,
      "phone": "01737-746095",
      "section_no": "C",
      "name": "রাকিবুজ্জামান সাব্বির"
    },
    {
      "id": 48,
      "phone": " +1 709-6904014 ",
      "section_no": "C",
      "name": "শামস বিন হারুন"
    },
    {
      "id": 49,
      "phone": "01749-006309",
      "section_no": "C",
      "name": "শাহারিয়ার সাকিব"
    },
    {
      "id": 50,
      "phone": "",
      "section_no": "C",
      "name": "ইশতিয়াক ইশরাক"
    },
    {
      "id": 51,
      "phone": "",
      "section_no": "C",
      "name": "ইশতিয়াক বিন হাবিব"
    },
    {
      "id": 52,
      "phone": "01798-997924",
      "section_no": "C",
      "name": "মোস্তাইন আহম্মেদ"
    },
    {
      "id": 53,
      "phone": "",
      "section_no": "C",
      "name": "আজিজুল হাকিম ( অনিক )"
    },
    {
      "id": 54,
      "phone": "",
      "section_no": "C",
      "name": "মোঃ নিরব হোসেন"
    },
    {
      "id": 55,
      "phone": "01617-201855",
      "section_no": "C",
      "name": "মাহমুদুল হাসান"
    },
    {
      "id": 56,
      "phone": "01728-325555",
      "section_no": "C",
      "name": "হুসাইন মেসবাহ"
    },
    {
      "id": 57,
      "phone": "",
      "section_no": "C",
      "name": "আল্লামা ওয়াস্তী"
    },
    {
      "id": 58,
      "phone": "01606-829032",
      "section_no": "C",
      "name": "মনজুরুল মোরসেদ ( মিথুন )"
    },
    {
      "id": 59,
      "phone": "",
      "section_no": "C",
      "name": "মোঃ সেলিম রেজা"
    },
    {
      "id": 60,
      "phone": "01791-918198",
      "section_no": "C",
      "name": "মাহফুজুল আলম রাহাত"
    },
    {
      "id": 61,
      "phone": "01711-013956",
      "section_no": "C",
      "name": "আসিম এ জেড জীম"
    }
  ]
}
